driver_selector/__init__.py
driver_selector/frontend/build/alonso.png
driver_selector/frontend/build/alonso_m.png
driver_selector/frontend/build/asset-manifest.json
driver_selector/frontend/build/bootstrap.min.css
driver_selector/frontend/build/hamilton.png
driver_selector/frontend/build/hamilton_m.png
driver_selector/frontend/build/index.html
driver_selector/frontend/build/max_verstappen.jpg
driver_selector/frontend/build/sainz.png
driver_selector/frontend/build/sainz_m.png
driver_selector/frontend/build/verstappen.png
driver_selector/frontend/build/verstappen_m.png
driver_selector/frontend/build/static/js/main.3281a89d.js
driver_selector/frontend/build/static/js/main.3281a89d.js.LICENSE.txt
driver_selector/frontend/build/static/js/main.3281a89d.js.map
driver_selector/frontend/build/static/js/main.5a64334a.js
driver_selector/frontend/build/static/js/main.5a64334a.js.LICENSE.txt
driver_selector/frontend/build/static/js/main.5a64334a.js.map
driver_selector/frontend/build/static/js/main.f001d22c.js
driver_selector/frontend/build/static/js/main.f001d22c.js.LICENSE.txt
driver_selector/frontend/build/static/js/main.f001d22c.js.map
driver_selector-0.0.4.dist-info/LICENSE
driver_selector-0.0.4.dist-info/METADATA
driver_selector-0.0.4.dist-info/WHEEL
driver_selector-0.0.4.dist-info/top_level.txt
driver_selector-0.0.4.dist-info/RECORD
